{
	"type": "premade",
	"map": {
		"players": [],
		"rooms": [
			{
				"rows": 2,
				"cols": 4,
				"description": "Starting Room",
				"tiles": [
					[
						[],
						[],
						[],
						[]
					],
					[
						[],
						[],
						[],
						[]
					]
				]
			},
			{
				"rows": 3,
				"cols": 3,
				"description": "Intermediate Room",
				"tiles": [
					[
						[],
						[],
						[]
					],
					[
						[],
						[],
						[]
					],
					[
						[],
						[],
						[]
					]
				]
			},
			{
				"rows": 4,
				"cols": 3,
				"description": "Goal Room",
				"tiles": [
					[
						[],
						[],
						[]
					],
					[
						[],
						[],
						[]
					],
					[
						[],
						[],
						[]
					],
					[
						[],
						[],
						[]
					]
				]
			}
		],
		"connections": [
			{
				"fromRoom": 0,
				"toRoom": 1,
				"fromTile": "0,2",
				"toTile": "2,1"
			},
			{
				"fromRoom": 1,
				"toRoom": 2,
				"fromTile": "0,1",
				"toTile": "3,1"
			}
		],
		"playerStartRooms": [],
		"goalRoom": 2
	},
	"clock": {
		"turnCounter": 0,
		"time": "day"
	}
}